disaggregators/__init__.py
disaggregators/disaggregator.py
disaggregators/disaggregation_modules/__init__.py
disaggregators/disaggregation_modules/disaggregation_module.py
disaggregators/disaggregation_modules/age/__init__.py
disaggregators/disaggregation_modules/continent/__init__.py
disaggregators/disaggregation_modules/gender/__init__.py
disaggregators/disaggregation_modules/pronoun/__init__.py
disaggregators/disaggregation_modules/religion/__init__.py
disaggregators-0.1.2.dist-info/LICENSE
disaggregators-0.1.2.dist-info/METADATA
disaggregators-0.1.2.dist-info/WHEEL
disaggregators-0.1.2.dist-info/top_level.txt
disaggregators-0.1.2.dist-info/RECORD
