Metadata-Version: 2.1
Name: disaggregators
Version: 0.1.2
Summary: HuggingFace community-driven open-source library for dataset disaggregation
Home-page: https://github.com/NimaBoscarino/disaggregators
Download-URL: https://github.com/NimaBoscarino/disaggregators/tags
Author: HuggingFace Inc.
Author-email: nima@huggingface.co
License: Apache 2.0
Keywords: machine learning evaluate evaluation disaggregation
Classifier: Development Status :: 1 - Planning
Classifier: Intended Audience :: Developers
Classifier: Intended Audience :: Education
Classifier: Intended Audience :: Science/Research
Classifier: License :: OSI Approved :: Apache Software License
Classifier: Operating System :: OS Independent
Classifier: Programming Language :: Python :: 3
Classifier: Programming Language :: Python :: 3.8
Classifier: Programming Language :: Python :: 3.9
Classifier: Programming Language :: Python :: 3.10
Classifier: Topic :: Scientific/Engineering :: Artificial Intelligence
Requires-Python: >=3.7.0
License-File: LICENSE
Requires-Dist: packaging
Requires-Dist: spacy
Requires-Dist: datasets
Requires-Dist: aenum (>=3.1.11)
Requires-Dist: sentence-transformers (>=2.2.2)
Requires-Dist: geograpy3
Requires-Dist: nltk
Requires-Dist: requests
Provides-Extra: dev
Requires-Dist: pytest ; extra == 'dev'
Requires-Dist: pytest-datadir ; extra == 'dev'
Requires-Dist: pytest-xdist ; extra == 'dev'
Requires-Dist: pytest-mock ; extra == 'dev'
Requires-Dist: nox ; extra == 'dev'
Requires-Dist: pandas ; extra == 'dev'
Requires-Dist: black (~=22.0) ; extra == 'dev'
Requires-Dist: flake8 (>=3.8.3) ; extra == 'dev'
Requires-Dist: isort (>=5.0.0) ; extra == 'dev'
Requires-Dist: pyyaml (>=5.3.1) ; extra == 'dev'
Provides-Extra: quality
Requires-Dist: black (~=22.0) ; extra == 'quality'
Requires-Dist: flake8 (>=3.8.3) ; extra == 'quality'
Requires-Dist: isort (>=5.0.0) ; extra == 'quality'
Requires-Dist: pyyaml (>=5.3.1) ; extra == 'quality'
Provides-Extra: tests
Requires-Dist: pytest ; extra == 'tests'
Requires-Dist: pytest-datadir ; extra == 'tests'
Requires-Dist: pytest-xdist ; extra == 'tests'
Requires-Dist: pytest-mock ; extra == 'tests'
Requires-Dist: nox ; extra == 'tests'
Requires-Dist: pandas ; extra == 'tests'
